BaseEmoji/__init__.py
BaseEmoji/codecs/BaseEmojiAbstract.py
BaseEmoji/codecs/__init__.py
BaseEmoji/codecs/anybase.py
BaseEmoji/codecs/group256.py
BaseEmoji/data/emojis.json
emojibase-0.0.2.data/data/x/emojis.json
emojibase-0.0.2.dist-info/LICENSE
emojibase-0.0.2.dist-info/METADATA
emojibase-0.0.2.dist-info/WHEEL
emojibase-0.0.2.dist-info/top_level.txt
emojibase-0.0.2.dist-info/RECORD
