Metadata-Version: 2.1
Name: emojibase
Version: 0.0.2
Summary: Encode any data to emojis
Home-page: https://github.com/tejado/BaseEmoji
Author: tejado
Author-email: tjado@maecke.de
License: UNKNOWN
Platform: UNKNOWN
Classifier: Programming Language :: Python :: 3
Classifier: License :: OSI Approved :: MIT License
Classifier: Operating System :: OS Independent
Requires-Python: >=3.6
Requires-Dist: regex
